tuesday/__init__.py
tuesday/_version.py
tuesday/py.typed
tuesday/core/__init__.py
tuesday/core/units.py
tuesday/core/instrument_models/__init__.py
tuesday/core/instrument_models/noise.py
tuesday/core/instrument_models/ska.py
tuesday/core/plotting/__init__.py
tuesday/core/plotting/powerspectra.py
tuesday/core/plotting/sliceplots.py
tuesday/core/postprocessing/__init__.py
tuesday/core/postprocessing/line_intensities.py
tuesday/core/summaries/__init__.py
tuesday/core/summaries/powerspectra.py
tuesday/core/summaries/psclasses.py
tuesday/simulators/__init__.py
tuesday/simulators/py21cmfast/lightcones.py
tuesday/simulators/py21cmfast/postprocessing/__init__.py
tuesday/simulators/py21cmfast/postprocessing/line_intensities.py
tuesday/simulators/py21cmfast/summaries/__init__.py
tuesday/simulators/py21cmfast/summaries/luminosity_functions.py
tuesday/simulators/py21cmfast/summaries/tau.py
tuesday_eor-2.3.0.dist-info/licenses/LICENSE
tuesday_eor-2.3.0.dist-info/METADATA
tuesday_eor-2.3.0.dist-info/WHEEL
tuesday_eor-2.3.0.dist-info/top_level.txt
tuesday_eor-2.3.0.dist-info/RECORD
