Metadata-Version: 2.4
Name: tuesday-eor
Version: 2.3.0
Summary: Tools for post-processing and computing summaries of 21cmFAST simulations
Author-email: Daniela Breitman <daniela.breitman@sns.it>, James Davies <james.davies@sns.it>, Steven Murray <murray.steveng@gmail.com>
License: MIT
Project-URL: Repository, https://github.com/21cmfast/tuesday
Project-URL: Issues, https://github.com/21cmfast/tuesday/issues
Project-URL: Changelog, https://github.com/21cmfast/tuesday/releases
Classifier: Development Status :: 4 - Beta
Classifier: Intended Audience :: Science/Research
Classifier: License :: OSI Approved :: MIT License
Classifier: Operating System :: POSIX
Classifier: Operating System :: Unix
Classifier: Programming Language :: Python
Classifier: Programming Language :: Python :: 3
Classifier: Programming Language :: Python :: 3 :: Only
Classifier: Programming Language :: Python :: Implementation :: CPython
Requires-Python: >=3.11
License-File: LICENSE
Requires-Dist: 21cmfast
Requires-Dist: 21cmsense>=2.0.0
Requires-Dist: astropy>=7.0.1
Requires-Dist: attrs>=25.3.0
Requires-Dist: numpy>=2
Requires-Dist: powerbox>=0.8.2
Requires-Dist: scipy>=1.15.2
Provides-Extra: 21cmfast
Requires-Dist: 21cmFAST>=4.0.0b; extra == "21cmfast"
Provides-Extra: tests
Requires-Dist: coverage; extra == "tests"
Requires-Dist: pytest-cov; extra == "tests"
Requires-Dist: pre-commit; extra == "tests"
Requires-Dist: pytest; extra == "tests"
Requires-Dist: sphinx; extra == "tests"
Provides-Extra: dev
Requires-Dist: tuesday-eor[21cmfast,tests]; extra == "dev"
Dynamic: license-file
